deepg/__init__.py
deepg-0.0.0.dist-info/METADATA
deepg-0.0.0.dist-info/WHEEL
deepg-0.0.0.dist-info/top_level.txt
deepg-0.0.0.dist-info/RECORD
