Metadata-Version: 2.1
Name: deepg
Version: 0.0.0
Summary: deepg
Home-page: https://www.aliyun.com
